cubed/__init__.py
cubed/_testing.py
cubed/backend_array_api.py
cubed/icechunk.py
cubed/random.py
cubed/spec.py
cubed/types.py
cubed/utils.py
cubed/array/__init__.py
cubed/array/nan_functions.py
cubed/array/overlap.py
cubed/array/pad.py
cubed/array_api/__init__.py
cubed/array_api/array_object.py
cubed/array_api/constants.py
cubed/array_api/creation_functions.py
cubed/array_api/data_type_functions.py
cubed/array_api/dtypes.py
cubed/array_api/elementwise_functions.py
cubed/array_api/indexing_functions.py
cubed/array_api/inspection.py
cubed/array_api/linalg.py
cubed/array_api/linear_algebra_functions.py
cubed/array_api/manipulation_functions.py
cubed/array_api/searching_functions.py
cubed/array_api/statistical_functions.py
cubed/array_api/utility_functions.py
cubed/core/__init__.py
cubed/core/array.py
cubed/core/groupby.py
cubed/core/gufunc.py
cubed/core/indexing.py
cubed/core/ops.py
cubed/core/optimization.py
cubed/core/plan.py
cubed/diagnostics/__init__.py
cubed/diagnostics/history.py
cubed/diagnostics/mem_usage.py
cubed/diagnostics/mem_warn.py
cubed/diagnostics/memray.py
cubed/diagnostics/rich.py
cubed/diagnostics/timeline.py
cubed/diagnostics/tqdm.py
cubed/primitive/__init__.py
cubed/primitive/blockwise.py
cubed/primitive/memory.py
cubed/primitive/rechunk.py
cubed/primitive/types.py
cubed/runtime/__init__.py
cubed/runtime/asyncio.py
cubed/runtime/backup.py
cubed/runtime/create.py
cubed/runtime/pipeline.py
cubed/runtime/types.py
cubed/runtime/utils.py
cubed/runtime/executors/__init__.py
cubed/runtime/executors/beam.py
cubed/runtime/executors/coiled.py
cubed/runtime/executors/dask.py
cubed/runtime/executors/lithops.py
cubed/runtime/executors/local.py
cubed/runtime/executors/modal.py
cubed/runtime/executors/ray.py
cubed/runtime/executors/spark.py
cubed/storage/__init__.py
cubed/storage/backend.py
cubed/storage/types.py
cubed/storage/virtual.py
cubed/storage/zarr.py
cubed/storage/backends/__init__.py
cubed/storage/backends/tensorstore.py
cubed-0.23.0.dist-info/licenses/LICENSE
cubed-0.23.0.dist-info/METADATA
cubed-0.23.0.dist-info/WHEEL
cubed-0.23.0.dist-info/top_level.txt
cubed-0.23.0.dist-info/RECORD
